README.rst
setup.cfg
setup.py
kolada/KoladaScraper.py
kolada/__init__.py
kolada_scraper.egg-info/PKG-INFO
kolada_scraper.egg-info/SOURCES.txt
kolada_scraper.egg-info/dependency_links.txt
kolada_scraper.egg-info/not-zip-safe
kolada_scraper.egg-info/requires.txt
kolada_scraper.egg-info/top_level.txt