Metadata-Version: 1.1
Name: kolada-scraper
Version: 0.0.2
Summary: A scraper of statistical data from api.kolada.se/v2 built on top of Statscraper.
Home-page: https://github.com/horriblesmell/kolada-scraper
Author: Sascha Granberg
Author-email: saschagranberg.jobb@gmail.com
License: MIT
Download-URL: https://github.com/horriblesmell/kolada-scraper/archive/0.0.2.tar.gz
Platform: UNKNOWN
